pyjapi/__init__.py
pyjapi/__main__.py
pyjapi/_types.py
pyjapi/cli.py
pyjapi/err.py
pyjapi/lib.py
pyjapi/util.py
pyjapi-0.7.0.dist-info/METADATA
pyjapi-0.7.0.dist-info/WHEEL
pyjapi-0.7.0.dist-info/entry_points.txt
pyjapi-0.7.0.dist-info/RECORD
