Metadata-Version: 2.1
Name: pyjapi
Version: 0.7.0
Summary: JAPI client
Project-URL: repository, https://git01.iis.fhg.de/ks-ip-lib/software/pyjapi
Keywords: click,japi,libjapi,python
Requires-Python: >=3.8
Requires-Dist: click>=8.0
Requires-Dist: python-dateutil
Requires-Dist: strconv
